opencf_core/__init__.py
opencf_core/base_converter.py
opencf_core/converter_app.py
opencf_core/enum.py
opencf_core/exceptions.py
opencf_core/file_handler.py
opencf_core/filetypes.py
opencf_core/io_handler.py
opencf_core/logging_config.py
opencf_core/mimes.py
opencf_core/py.typed
opencf_core/utils.py
opencf_core-0.3.4.dist-info/METADATA
opencf_core-0.3.4.dist-info/WHEEL
opencf_core-0.3.4.dist-info/RECORD
