Metadata-Version: 2.1
Name: opencf-core
Version: 0.3.4
Summary: A robust framework for handling file conversion tasks in Python
Home-page: https://github.com/Hermann-web/opencf-core
License: MIT
Keywords: file conversion,data processing,file formats
Author: Hermann Agossou
Author-email: agossouhermann7@gmail.com
Maintainer: Hermann Agossou
Maintainer-email: agossouhermann7@gmail.com
Requires-Python: >=3.7,<4.0
Classifier: Development Status :: 4 - Beta
Classifier: Intended Audience :: Developers
Classifier: License :: OSI Approved :: MIT License
Classifier: Programming Language :: Python :: 3
Classifier: Programming Language :: Python :: 3.7
Classifier: Programming Language :: Python :: 3.8
Classifier: Programming Language :: Python :: 3.9
Classifier: Programming Language :: Python :: 3.10
Classifier: Programming Language :: Python :: 3.11
Classifier: Programming Language :: Python :: 3.12
Classifier: Topic :: Software Development :: Libraries :: Python Modules
Requires-Dist: aenum (>=3.1.15,<4.0.0)
Requires-Dist: python-magic (>=0.4.27,<0.5.0)
Project-URL: Documentation, https://opencf-core.readthedocs.io
Project-URL: Repository, https://github.com/Hermann-web/opencf-core
